{
    "organization": [
        {
            "id": 1,
            "organisation_type": "МКК",
            "name_short": "ООО Горбенко",
            "name_full": "ООО Горбенко Игорь Денисович",
            "brand_name": "ЫЫЫЫ",
            "inn": 1231231,
            "ogrn": 2341234,
            "location_reg": "г. Москва ул. Ямная",
            "date_reg": "2024-04-24",
            "email": "gorbenko@gmail.com",
            "phone": "88005553535",
            "rating": 3.2

        },
        {
            "id": 2,
            "organisation_type": "МФК",
            "name_short": "ВТБ",
            "name_full": "ВТБ банк",
            "brand_name": "ВТБ",
            "inn": 1121,
            "ogrn": 223423,
            "location_reg": "г. Санкт-Петербург Покровский бул. 11",
            "date_reg": "2024-04-20",
            "email": "vtb@gmail.com",
            "phone": "88005553534",
            "rating": 4.6
        },
        {            
            "id": 3,
            "organisation_type": "КПК",
            "name_short": "ООО СуперБанк",
            "name_full": "ООО КПК СуперБанк",
            "brand_name": "СуперБанк",
            "inn": 11212345,
            "ogrn": 223423789,
            "location_reg": "г. Череповец ул. Городецкая",
            "date_reg": "2024-05-02",
            "email": "superbank@gmail.com",
            "phone": "88005553532",
            "rating": 4.2
        },
        {
            "id": 4,
            "organisation_type": "CКПК",
            "name_short": "ООО КрутойЗаём",
            "name_full": "ООО СКПК КрутойЗаём",
            "brand_name": "КрутойЗаём",
            "inn": 1987654,
            "ogrn": 2234345679,
            "location_reg": "г. Москва Красная площадь 7",
            "date_reg": "2024-01-02",
            "email": "coolzaem@gmail.com",
            "phone": "88005553531",
            "rating": 2.9
        },
        {
            "id": 5,
            "organisation_type": "Ломбард",
            "name_short": "ООО НесиЗолотоКНам",
            "name_full": "ООО Ломбард НесиЗолотоКНам",
            "brand_name": "НесиЗолотоКНам",
            "inn": 9988789,
            "ogrn": 9494949494,
            "location_reg": "г. Тверь просп. Победы",
            "date_reg": "2022-01-02",
            "email": "bringgold@gmail.com",
            "phone": "88005553530",
            "rating": 3.6
        },
        {
            "id": 6,
            "organisation_type": "МФО",
            "name_short": "ООО Финансист",
            "name_full": "ООО Финансист Иванов",
            "brand_name": "Финансист",
            "inn": 33445566,
            "ogrn": 11223344,
            "location_reg": "г. Новосибирск ул. Ленина 10",
            "date_reg": "2023-11-15",
            "email": "finansist@gmail.com",
            "phone": "88005553536",
            "rating": 4.0
        },
        {
            "id": 7,
            "organisation_type": "МКК",
            "name_short": "ООО ДоступныйКредит",
            "name_full": "ООО МКК ДоступныйКредит",
            "brand_name": "ДоступныйКредит",
            "inn": 66778899,
            "ogrn": 99887766,
            "location_reg": "г. Казань ул. Баумана 5",
            "date_reg": "2023-03-30",
            "email": "credit@gmail.com",
            "phone": "88005553537",
            "rating": 3.8
        },
        {
            "id": 8,
            "organisation_type": "КПК",
            "name_short": "ООО НадежныйЗаем",
            "name_full": "ООО КПК НадежныйЗаем",
            "brand_name": "НадежныйЗаем",
            "inn": 22334455,
            "ogrn": 77665544,
            "location_reg": "г. Омск ул. Гагарина 7",
            "date_reg": "2022-06-18",
            "email": "nadezhnyzaem@gmail.com",
            "phone": "88005553538",
            "rating": 4.5
        },
        {
            "id": 9,
            "organisation_type": "МФК",
            "name_short": "ООО ЛиквидКапитал",
            "name_full": "ООО МФК ЛиквидКапитал",
            "brand_name": "ЛиквидКапитал",
            "inn": 99881122,
            "ogrn": 33445577,
            "location_reg": "г. Екатеринбург ул. Куйбышева 12",
            "date_reg": "2024-05-01",
            "email": "liquidcapital@gmail.com",
            "phone": "88005553539",
            "rating": 4.7
        },
        {
            "id": 10,
            "organisation_type": "СКПК",
            "name_short": "ООО ФинансГарант",
            "name_full": "ООО СКПК ФинансГарант",
            "brand_name": "ФинансГарант",
            "inn": 77661188,
            "ogrn": 55443322,
            "location_reg": "г. Самара ул. Советская 6",
            "date_reg": "2022-12-25",
            "email": "finansgarant@gmail.com",
            "phone": "88005553540",
            "rating": 4.1
        },
        {
            "id": 11,
            "organisation_type": "Ломбард",
            "name_short": "ООО ЭкспрессКредит",
            "name_full": "ООО Ломбард ЭкспрессКредит",
            "brand_name": "ЭкспрессКредит",
            "inn": 77665588,
            "ogrn": 11223355,
            "location_reg": "г. Москва ул. Тверская 9",
            "date_reg": "2023-02-18",
            "email": "expresscredit@gmail.com",
            "phone": "88005553541",
            "rating": 3.9
        },
        {
            "id": 12,
            "organisation_type": "МКК",
            "name_short": "ООО БыстрыйЗаем",
            "name_full": "ООО МКК БыстрыйЗаем",
            "brand_name": "БыстрыйЗаем",
            "inn": 88990011,
            "ogrn": 33445566,
            "location_reg": "г. Санкт-Петербург ул. Невский 20",
            "date_reg": "2023-07-01",
            "email": "fastloan@gmail.com",
            "phone": "88005553542",
            "rating": 4.3
        },
        {
            "id": 13,
            "organisation_type": "КПК",
            "name_short": "ООО ТрастФинанс",
            "name_full": "ООО КПК ТрастФинанс",
            "brand_name": "ТрастФинанс",
            "inn": 55667788,
            "ogrn": 11223366,
            "location_reg": "г. Волгоград ул. Мира 5",
            "date_reg": "2023-03-12",
            "email": "trustfinance@gmail.com",
            "phone": "88005553543",
            "rating": 4.4
        },
        {
            "id": 14,
            "organisation_type": "МФК",
            "name_short": "ООО МегаКредит",
            "name_full": "ООО МФК МегаКредит",
            "brand_name": "МегаКредит",
            "inn": 66778800,
            "ogrn": 99887711,
            "location_reg": "г. Красноярск ул. Ленина 15",
            "date_reg": "2024-02-01",
            "email": "megacredit@gmail.com",
            "phone": "88005553544",
            "rating": 4.6
        },
        {
            "id": 15,
            "organisation_type": "СКПК",
            "name_short": "ООО СоюзКредит",
            "name_full": "ООО СКПК СоюзКредит",
            "brand_name": "СоюзКредит",
            "inn": 77889911,
            "ogrn": 11224455,
            "location_reg": "г. Уфа ул. Комсомольская 8",
            "date_reg": "2023-09-20",
            "email": "unioncredit@gmail.com",
            "phone": "88005553545",
            "rating": 4.2
        }
    ],
    "products": [
        {
            "id": 101,
            "id_org": 1,
            "product_type": "заем",
            "amount_min" : 10000,
            "amount_max" : 100000,
            "term_min" : 30, 
            "term_max" : 120,
            "rate" : 0.3,
            "method_reg" : "офлайн/онлайн"
        },
        {
            "id": 102,
            "id_org": 1,
            "product_type": "заем",
            "amount_min" : 100000,
            "amount_max" : 500000,
            "term_min" : 90, 
            "term_max" : 360,
            "rate" : 0.2,
            "method_reg" : "офлайн"
        },
        {
            "id": 103,
            "id_org": 2,
            "product_type": "заем",
            "amount_min" : 10000,
            "amount_max" : 30000,
            "term_min" : 7, 
            "term_max" : 30,
            "rate" : 0.17,
            "method_reg" : "офлайн/онлайн"
        }, 
        {
            "id": 104,
            "id_org": 2,
            "product_type": "сбережения",
            "amount_min" : 1500000,
            "amount_max" : 10000000,
            "term_min" : 90, 
            "term_max" : 360,
            "rate" : 0.14,
            "method_reg" : "онлайн"
        },
        {
            "id": 105,
            "id_org": 3,
            "product_type": "заем",
            "amount_min" : 1000,
            "amount_max" : 30000,
            "term_min" : 7, 
            "term_max" : 30,
            "rate" : 0.16,
            "method_reg" : "офлайн"
        },
        {
            "id": 106,
            "id_org": 3,
            "product_type": "сбережения",
            "amount_min" : 20000,
            "amount_max" : 100000,
            "term_min" : 60, 
            "term_max" : 90,
            "rate" : 0.155,
            "method_reg" : "офлайн"
        },
        {
            "id": 107,
            "id_org": 4,
            "product_type": "займ",
            "amount_min" : 5000,
            "amount_max" : 50000,
            "term_min" : 14, 
            "term_max" : 60,
            "rate" : 0.151,
            "method_reg" : "офлайн"
        },
        {
            "id": 108,
            "id_org": 4,
            "product_type": "сбережения",
            "amount_min" : 10000,
            "amount_max" : 100000,
            "term_min" : 30, 
            "term_max" : 60,
            "rate" : 0.148,
            "method_reg" : "офлайн"
        },
        {
            "id": 109,
            "id_org": 5,
            "product_type": "займ",
            "amount_min" : 10000,
            "amount_max" : 50000,
            "term_min" : 7, 
            "term_max" : 60,
            "rate" : 0.2,
            "method_reg" : "офлайн"
        },
        {
            "id": 110,
            "id_org": 5,
            "product_type": "займ",
            "amount_min" : 50000,
            "amount_max" : 100000,
            "term_min" : 60, 
            "term_max" : 180,
            "rate" : 0.25,
            "method_reg" : "офлайн"
        },
        {
            "id": 111,
            "id_org": 6,
            "product_type": "заем",
            "amount_min": 10000,
            "amount_max": 200000,
            "term_min": 30,
            "term_max": 120,
            "rate": 0.18,
            "method_reg": "офлайн/онлайн"
        },
        {
            "id": 112,
            "id_org": 6,
            "product_type": "сбережения",
            "amount_min": 100000,
            "amount_max": 500000,
            "term_min": 60,
            "term_max": 360,
            "rate": 0.12,
            "method_reg": "онлайн"
        },
        {
            "id": 113,
            "id_org": 7,
            "product_type": "заем",
            "amount_min": 5000,
            "amount_max": 100000,
            "term_min": 14,
            "term_max": 90,
            "rate": 0.19,
            "method_reg": "офлайн"
        },
        {
            "id": 114,
            "id_org": 7,
            "product_type": "сбережения",
            "amount_min": 50000,
            "amount_max": 200000,
            "term_min": 30,
            "term_max": 180,
            "rate": 0.13,
            "method_reg": "онлайн"
        },
        {
            "id": 115,
            "id_org": 8,
            "product_type": "заем",
            "amount_min": 2000,
            "amount_max": 50000,
            "term_min": 7,
            "term_max": 45,
            "rate": 0.22,
            "method_reg": "офлайн"
        },
        {
            "id": 116,
            "id_org": 8,
            "product_type": "сбережения",
            "amount_min": 20000,
            "amount_max": 100000,
            "term_min": 60,
            "term_max": 120,
            "rate": 0.15,
            "method_reg": "офлайн"
        },
        {
            "id": 117,
            "id_org": 9,
            "product_type": "заем",
            "amount_min": 10000,
            "amount_max": 100000,
            "term_min": 30,
            "term_max": 90,
            "rate": 0.21,
            "method_reg": "офлайн/онлайн"
        },
        {
            "id": 118,
            "id_org": 9,
            "product_type": "сбережения",
            "amount_min": 1500000,
            "amount_max": 5000000,
            "term_min": 90,
            "term_max": 365,
            "rate": 0.14,
            "method_reg": "онлайн"
        },
        {
            "id": 119,
            "id_org": 10,
            "product_type": "заем",
            "amount_min": 3000,
            "amount_max": 50000,
            "term_min": 14,
            "term_max": 60,
            "rate": 0.17,
            "method_reg": "офлайн"
        },
        {
            "id": 120,
            "id_org": 10,
            "product_type": "сбережения",
            "amount_min": 10000,
            "amount_max": 50000,
            "term_min": 30,
            "term_max": 180,
            "rate": 0.13,
            "method_reg": "офлайн"
        },
        {
            "id": 121,
            "id_org": 11,
            "product_type": "заем",
            "amount_min": 5000,
            "amount_max": 50000,
            "term_min": 14,
            "term_max": 90,
            "rate": 0.24,
            "method_reg": "офлайн/онлайн"
        },
        {
            "id": 122,
            "id_org": 11,
            "product_type": "заем",
            "amount_min": 50000,
            "amount_max": 300000,
            "term_min": 30,
            "term_max": 180,
            "rate": 0.18,
            "method_reg": "офлайн"
        },
        {
            "id": 123,
            "id_org": 12,
            "product_type": "заем",
            "amount_min": 5000,
            "amount_max": 20000,
            "term_min": 5,
            "term_max": 21,
            "rate": 0.15,
            "method_reg": "офлайн/онлайн"
        },
        {
            "id": 124,
            "id_org": 12,
            "product_type": "сбережения",
            "amount_min": 1000000,
            "amount_max": 5000000,
            "term_min": 60,
            "term_max": 180,
            "rate": 0.12,
            "method_reg": "онлайн"
        },
        {
            "id": 125,
            "id_org": 13,
            "product_type": "заем",
            "amount_min": 500,
            "amount_max": 15000,
            "term_min": 5,
            "term_max": 21,
            "rate": 0.14,
            "method_reg": "офлайн/онлайн"
        },
        {
            "id": 126,
            "id_org": 14,
            "product_type": "заем",
            "amount_min": 20000,
            "amount_max": 150000,
            "term_min": 30,
            "term_max": 180,
            "rate": 0.22,
            "method_reg": "онлайн"
        },
        {
            "id": 127,
            "id_org": 15,
            "product_type": "заем",
            "amount_min": 10000,
            "amount_max": 100000,
            "term_min": 14,
            "term_max": 90,
            "rate": 0.20,
            "method_reg": "офлайн"
        },
        {
            "id": 128,
            "id_org": 15,
            "product_type": "заем",
            "amount_min": 0,
            "amount_max": 100000000000,
            "term_min": 0,
            "term_max": 100000,
            "rate": 0.0001,
            "method_reg": "офлайн"
        },
        {
            "id": 129,
            "id_org": 10,
            "product_type": "сбережения",
            "amount_min": 0,
            "amount_max": 5000000000000,
            "term_min": 0,
            "term_max": 1800000,
            "rate": 0.8,
            "method_reg": "офлайн"
        }
    ]
}